[
  {
    "event": "南韓慶尚北道野火",
    "region": "國外",
    "cover": "https://images.newtalk.tw/resize_action2/800/album/news/963/67e62d7139389.jpg",
    "date": "2025-03-28",
    "recent_update": "2025-03-28",
    "location": [
      "韓國 慶尚北道",
      "義城郡",
      "安東市",
      "盈德郡",
      "英陽郡",
      "青松郡",
      "慶尚南道",
      "山清",
      "河東郡"
    ],
    "overview": "韓國東南部山林大火造成至少28人死亡，65人受傷，40,000人撤離家園。火災過火面積達48,150公頃，約佔首爾總面積的80%。受災設施包括3,481處房屋和農業設施，目前仍有8,078人安置在避難所。火勢撲滅進度不一，部分地區火勢仍未完全控制。文化遺產如古雲寺等受到嚴重破壞。",
    "daily_records": [
      {
        "date": "2025-03-28",
        "content": "韓國東南部發生史上最嚴重山林大火，火勢蔓延超過70公里，造成至少28人死亡，65人受傷，40,000人撤離。",
        "location": [
          "韓國 慶尚北道",
          "義城郡",
          "安東市",
          "盈德郡",
          "英陽郡",
          "青松郡",
          "慶尚南道",
          "山清",
          "河東郡"
        ]
      }
    ],
    "links": [
      {
        "source": {
          "publisher": "Newtalk新聞",
          "author": "Newtalk新聞"
        },
        "url": "https://newtalk.tw/news/view/2025-03-28/962838",
        "title": "韓國史上最嚴重山林大火！4.5萬公頃森林毀滅已釀28死、逾4萬人撤離| 政治",
        "publish_date": "2025-03-28",
        "location": [
          "韓國 慶尚北道",
          "義城郡",
          "安東市",
          "盈德郡",
          "英陽郡",
          "青松郡",
          "慶尚南道",
          "山清",
          "河東郡"
        ],
        "summary": "韓國東南部山林大火造成至少28人死亡，65人受傷，40,000人撤離家園。火災過火面積達48,150公頃，約佔首爾總面積的80%。受災設施包括3,481處房屋和農業設施，目前仍有8,078人安置在避難所。火勢撲滅進度不一，部分地區火勢仍未完全控制。文化遺產如古雲寺等受到嚴重破壞。"
      }
    ]
  },
  {
    "event": "印尼摩鹿加地震",
    "region": "國外",
    "cover": "https://pgw.udn.com.tw/gw/photo.php?u=https://uc.udn.com.tw/photo/2025/04/01/realtime/31763630.jpg&x=0&y=0&sw=0&sh=0&sl=W&fw=1050&exp=3600&exp=3600",
    "date": "2025-04-01",
    "recent_update": "2025-04-01",
    "location": [
      "印尼 摩鹿加",
      "東帝汶聖保羅"
    ],
    "overview": "2025年4月1日傍晚6時15分，印尼摩鹿加附近發生規模5.7地震，震央位於東帝汶聖保羅東北東方205公里，深度141公里，目前未有災情傳出。",
    "daily_records": [
      {
        "date": "2025-04-01",
        "content": "印尼摩鹿加附近發生規模5.7地震，震央位於東帝汶東北東方，深度141公里。",
        "location": [
          "印尼 摩鹿加",
          "東帝汶聖保羅"
        ]
      }
    ],
    "links": [
      {
        "source": {
          "publisher": "經濟日報",
          "author": "經濟日報"
        },
        "url": "https://money.udn.com/money/story/5599/8647301",
        "title": "東南亞再傳地震 印尼周邊發生規模5.7地震",
        "publish_date": "2025-04-01",
        "location": [
          "印尼 摩鹿加",
          "東帝汶聖保羅"
        ],
        "summary": "目前未有災情傳出，無具體損失數據。"
      }
    ]
  },
  {
    "event": "東加東加王國地震",
    "region": "國外",
    "cover": "",
    "date": "2025-03-30",
    "recent_update": "2025-03-31",
    "location": [
      "東加王國 東加王國",
      "努瓜婁發",
      "東加塔布島"
    ],
    "overview": "東加王國附近於2025年3月30日發生7.0至7.3級地震，震央位於東加塔布島東北方約100公里，深度10至29公里。隨後發布海嘯警報，但後續解除。無人員傷亡或建築受損報告，居民一度撤離至內陸或高地，後返回家園。台灣氣象署發布海嘯消息，但台灣被列為不受影響區域。",
    "daily_records": [
      {
        "date": "2025-03-30",
        "content": "東加外海發生規模7.1強震，震央位於東加塔布東北約100公里，深度僅10公里，隨後發布海嘯警報。",
        "location": [
          "東加 東加塔布",
          "東加主島"
        ]
      },
      {
        "date": "2025-03-31",
        "content": "東加王國附近發生7.0地震，海嘯警報後解除，無傷亡或建築受損。",
        "location": [
          "東加王國 東加王國",
          "努瓜婁發",
          "東加塔布島"
        ]
      },
      {
        "date": "2025-03-31",
        "content": "東加外海發生規模7.3強震，引發海嘯警報，但台灣民眾無須過度擔心。",
        "location": [
          "東加 塔布島",
          "東加群島"
        ]
      }
    ],
    "links": [
      {
        "source": {
          "publisher": "經濟日報",
          "author": "經濟日報"
        },
        "url": "https://money.udn.com/money/story/5599/8642792",
        "title": "東加王國附近7.0地震 海嘯警報解除迄無傷亡災損",
        "publish_date": "2025-03-31",
        "location": [
          "東加王國 東加王國",
          "努瓜婁發",
          "東加塔布島"
        ],
        "summary": "東加王國附近發生7.0地震，隨後發生6.1地震，海嘯警報一度發布後解除。無人員傷亡或建築受損報告，居民一度撤離至內陸或高地，後返回家園。"
      },
      {
        "source": {
          "publisher": "自由時報",
          "author": "自由時報"
        },
        "url": "https://news.ltn.com.tw/news/world/breakingnews/4996677",
        "title": "大洋洲島國東加規模7.1強震 海嘯警報發布",
        "publish_date": "2025-03-30",
        "location": [
          "東加 東加塔布",
          "東加主島"
        ],
        "summary": "東加發生規模7.1的地震，震央距離東加塔布約100公里，深度10公里。美國太平洋海嘯警報中心發布海嘯警報，警告震央300公里內的海岸可能出現0.3到1公尺的海嘯。未提及具體的損失數據。"
      },
      {
        "source": {
          "publisher": "自由時報",
          "author": "自由時報"
        },
        "url": "https://news.ltn.com.tw/news/life/breakingnews/4996751",
        "title": "東加規模7.3強震觸發海嘯警報 專家曝對台影響",
        "publish_date": "2025-03-31",
        "location": [
          "東加 塔布島",
          "東加群島"
        ],
        "summary": "東加外海發生規模7.3強震，震央在塔布島東北方外海，美國太平洋海嘯警報中心發出海嘯警報，台灣氣象署發布海嘯消息但後解除。目前東加群島上未傳出災情，台灣被列為不受影響區域。"
      }
    ]
  },
  {
    "event": "泰國曼谷地震",
    "region": "國外",
    "cover": "https://ichef.bbci.co.uk/ace/ws/640/cpsprodpb/94bd/live/e9f1a480-0d14-11f0-ba12-8d27eb561761.jpg.webp",
    "date": "2025-03-30",
    "recent_update": "2025-03-30",
    "location": [
      "泰國 曼谷",
      "緬甸中部",
      "泰國邊境"
    ],
    "overview": "緬甸中部於2025年3月28日發生7.7級地震，餘震6.4級，導致泰國曼谷一棟30層大樓倒塌，造成3人死亡，81人被困。救援工作正在進行中，現場有大量救援車輛和重型機械。",
    "daily_records": [
      {
        "date": "2025-03-30",
        "content": "泰國曼谷一棟30層大樓因緬甸地震倒塌，救援人員正在廢墟中搜尋倖存者。",
        "location": [
          "泰國 曼谷",
          "緬甸中部",
          "泰國邊境"
        ]
      }
    ],
    "links": [
      {
        "source": {
          "publisher": "BBC News 中文",
          "author": "BBC News 中文"
        },
        "url": "https://www.bbc.com/zhongwen/articles/cewglkxg49zo/trad",
        "title": "BBC記者現場目擊：救援人員在倒塌的30層建築廢墟中拼命搜尋倖存者",
        "publish_date": "2025-03-30",
        "location": [
          "泰國 曼谷",
          "緬甸中部",
          "泰國邊境"
        ],
        "summary": "緬甸7.7級地震導致泰國曼谷一棟30層大樓倒塌，已確認3人死亡，81人被困。救援人員正在努力搜救，現場有大量救援車輛和重型機械。建築耗資約5900萬美元，現已成為一片瓦礫。"
      }
    ]
  },
  {
    "event": "緬甸曼德勒地震",
    "region": "國外",
    "cover": "https://ichef.bbci.co.uk/images/ic/512xn/p0l0yq7g.jpg.webp",
    "date": "2025-03-28",
    "recent_update": "2025-04-03",
    "location": [
      "緬甸 實皆市",
      "曼德勒",
      "仰光",
      "內比都",
      "泰國曼谷",
      "中國雲南",
      "中國西雙版納",
      "中國德宏",
      "中國昆明",
      "中國麗江",
      "中國保山",
      "中國大理",
      "中國貴州",
      "中國廣西",
      "中國四川攀枝花"
    ],
    "overview": "2025年3月28日，緬甸中部發生7.7級強烈地震，震央位於薩加因西北偏北16公里，震源深度10公里，造成曼德勒等地嚴重破壞，至少1700人死亡，數千人受傷，失蹤人數不詳。曼德勒機場跑道受損，救援通道受阻，醫療用品短缺，停電加劇災情。泰國曼谷一棟30層高樓倒塌，8人遇難，117人下落不明。緬甸軍政府首次向國際求援，國際援助開始進入緬甸，但尚未抵達最嚴重災區。",
    "daily_records": [
      {
        "date": "2025-03-28",
        "content": "緬甸發生7.7級地震，造成至少144人死亡，732人受傷，曼德勒和仰光受災嚴重。",
        "location": [
          "緬甸 實皆市",
          "曼德勒",
          "仰光",
          "內比都",
          "泰國曼谷",
          "中國雲南",
          "中國西雙版納",
          "中國德宏",
          "中國昆明",
          "中國麗江",
          "中國保山",
          "中國大理",
          "中國貴州",
          "中國廣西",
          "中國四川攀枝花"
        ]
      },
      {
        "date": "2025-03-28",
        "content": "緬甸中部發生7.7級強烈地震，震央位於薩加因西北偏北16公里，震源深度10公里，鄰國泰國、越南、印度等地均有震感。",
        "location": [
          "緬甸 薩加因",
          "曼德勒",
          "曼谷",
          "清邁",
          "德里",
          "雲南",
          "四川"
        ]
      },
      {
        "date": "2025-03-28",
        "content": "緬甸發生7.7級強烈地震，震感遍及中國和泰國，泰國進入緊急狀態。",
        "location": [
          "緬甸 曼德勒",
          "曼谷"
        ]
      },
      {
        "date": "2025-03-30",
        "content": "緬甸發生毀滅性地震，造成1600多人死亡，曼德勒大部分地區夷為平地，搜救工作因設備匱乏受阻。",
        "location": [
          "緬甸 曼德勒",
          "仰光",
          "內比都",
          "實皆省",
          "皎塞縣辛特凱鎮",
          "撣邦北部瑙喬",
          "昌烏鎮"
        ]
      },
      {
        "date": "2025-03-31",
        "content": "緬甸3月28日發生7.7級地震，救援進度緩慢，軍政府空襲持續，災情難以釐清。",
        "location": [
          "緬甸 內比都",
          "曼德勒",
          "曼谷"
        ]
      },
      {
        "date": "2025-04-01",
        "content": "緬甸軍政府淡化地震災情，BBC事實查核團隊比對衛星照片，訪問曼德勒居民，拼湊實際災情。",
        "location": [
          "緬甸 曼德勒"
        ]
      },
      {
        "date": "2025-04-03",
        "content": "緬甸曼德勒市遭受強震，街頭瀰漫腐屍味，救援人員不足，民眾徒手挖掘。",
        "location": [
          "緬甸 曼德勒市"
        ]
      }
    ],
    "links": [
      {
        "source": {
          "publisher": "BBC News 中文",
          "author": "BBC News 中文"
        },
        "url": "https://www.bbc.com/zhongwen/articles/cy5n53vk7q9o/trad",
        "title": "緬甸強烈地震：逾百人遇難，軍政府罕有向國際求援，泰國曼谷高樓倒塌",
        "publish_date": "2025-03-28",
        "location": [
          "緬甸 實皆市",
          "曼德勒",
          "仰光",
          "內比都",
          "泰國曼谷",
          "中國雲南",
          "中國西雙版納",
          "中國德宏",
          "中國昆明",
          "中國麗江",
          "中國保山",
          "中國大理",
          "中國貴州",
          "中國廣西",
          "中國四川攀枝花"
        ],
        "summary": "緬甸地震造成至少144人死亡，732人受傷，曼德勒和仰光受災嚴重。泰國曼谷一棟30層高樓倒塌，8人遇難，117人下落不明。緬甸軍政府首次向國際求援，災害影響範圍包括緬甸中部和泰國部分地區。"
      },
      {
        "source": {
          "publisher": "BBC News 中文",
          "author": "BBC News 中文"
        },
        "url": "https://www.bbc.com/zhongwen/articles/c3evjv4pkzpo/trad",
        "title": "緬甸地震死亡人數超過1600人，民眾徒手挖掘倖存者",
        "publish_date": "2025-03-30",
        "location": [
          "緬甸 曼德勒",
          "仰光",
          "內比都",
          "實皆省",
          "皎塞縣辛特凱鎮",
          "撣邦北部瑙喬",
          "昌烏鎮"
        ],
        "summary": "緬甸地震造成1600多人死亡，曼德勒市區嚴重受損，超過1500棟建築物受損。搜救工作因設備和通訊問題受阻，國際援助開始進入緬甸。曼德勒機場跑道受損，救援通道受阻，醫療用品短缺，停電加劇災情。"
      },
      {
        "source": {
          "publisher": "Newtalk新聞",
          "author": "Newtalk新聞"
        },
        "url": "https://newtalk.tw/news/view/2025-03-28/962869",
        "title": "緬甸7.7強烈淺層地震！泰越印中都感搖晃屋倒橋斷傷亡不明| 國際",
        "publish_date": "2025-03-28",
        "location": [
          "緬甸 薩加因",
          "曼德勒",
          "曼谷",
          "清邁",
          "德里",
          "雲南",
          "四川"
        ],
        "summary": "緬甸中部發生7.7級地震，震央靠近曼德勒，目前未有具體傷亡或損失報告。泰國曼谷距離震央約700公里，當地高樓搖晃明顯，民眾驚慌撤離。緬甸政局動盪，通訊與救援可能受限，國際社會密切關注後續發展。"
      },
      {
        "source": {
          "publisher": "BBC News 中文",
          "author": "BBC News 中文"
        },
        "url": "https://www.bbc.com/zhongwen/articles/c15q5v2n40no/trad",
        "title": "緬甸7.7級強烈地震 至少81人失蹤、百人死亡",
        "publish_date": "2025-03-28",
        "location": [
          "緬甸 曼德勒",
          "曼谷"
        ],
        "summary": "緬甸地震造成至少81人失蹤，數百人死亡。泰國曼谷一棟未完工高樓倒塌，81名建築工人失蹤。緬甸政治動盪影響救援和資訊獲取。"
      },
      {
        "source": {
          "publisher": "BBC News 中文",
          "author": "BBC News 中文"
        },
        "url": "https://www.bbc.com/zhongwen/articles/cj9ejzxgr1jo/trad",
        "title": "BBC事實查核：緬甸軍政府淡化地震災情？",
        "publish_date": "2025-04-01",
        "location": [
          "緬甸 曼德勒"
        ],
        "summary": "緬甸軍政府淡化地震災情，實際災情難以掌握。軍方在受災區加強攻勢，救災工作因政局動盪而困難。具體損失數據未明，但衛星影像顯示災情嚴重。"
      },
      {
        "source": {
          "publisher": "BBC News 中文",
          "author": "BBC News 中文"
        },
        "url": "https://www.bbc.com/zhongwen/articles/c5y6g77305wo/trad",
        "title": "走進緬甸震央曼德勒：瀰漫腐屍味的絕望之城",
        "publish_date": "2025-04-03",
        "location": [
          "緬甸 曼德勒市"
        ],
        "summary": "曼德勒市因地震造成巨大破壞，救援人員匱乏，醫院不堪重負，許多人仍在等待救援，無法估計具體的死亡人數和財產損失。"
      },
      {
        "source": {
          "publisher": "BBC News 中文",
          "author": "BBC News 中文"
        },
        "url": "https://www.bbc.com/zhongwen/articles/cwy7wy222z8o/trad",
        "title": "緬甸地震：死傷數千搜救緩慢 叛軍斥軍政府持續空襲",
        "publish_date": "2025-03-31",
        "location": [
          "緬甸 內比都",
          "曼德勒",
          "曼谷"
        ],
        "summary": "緬甸地震已造成超過1700人死亡，數千人受傷，失蹤人數不詳。美國地質調查局估計死亡人數可能突破一萬。災區內比都和曼德勒受災嚴重，軍政府限制通訊，影響救援和援助分配。泰國曼谷一棟大樓倒塌，數十人失蹤。"
      }
    ]
  },
  {
    "event": "美國密蘇里州大雨",
    "region": "國外",
    "cover": "",
    "date": "2025-04-03",
    "recent_update": "2025-04-03",
    "location": [
      "美國 密蘇里州",
      "阿肯色州",
      "田納西州",
      "密西西比州",
      "印第安納州",
      "伊利諾州",
      "肯塔基州",
      "奧克拉荷馬州",
      "密西根州",
      "內華達鎮"
    ],
    "overview": "美國中南部地區遭遇龍捲風與暴雨襲擊，造成至少1人死亡，超過35萬用戶斷電。預計未來幾天將有世代級洪災，部分地區可能降下38.1公分的雨量，河流可能決堤，引發災難性洪水。受影響地區包括密蘇里州、阿肯色州、田納西州、密西西比州、印第安納州、伊利諾州、肯塔基州與奧克拉荷馬州。",
    "daily_records": [
      {
        "date": "2025-04-03",
        "content": "美國中南部遭龍捲風與暴雨襲擊，造成至少1人死亡，數百萬人處於警報中。",
        "location": [
          "美國 密蘇里州",
          "阿肯色州",
          "田納西州",
          "密西西比州",
          "印第安納州",
          "伊利諾州",
          "肯塔基州",
          "奧克拉荷馬州",
          "密西根州",
          "內華達鎮"
        ]
      }
    ],
    "links": [
      {
        "source": {
          "publisher": "經濟日報",
          "author": "經濟日報"
        },
        "url": "https://money.udn.com/money/story/10511/8651577?from=edn_subcatelist_cate",
        "title": "美國中、南部遭龍捲風與暴雨襲擊 已知1人死亡",
        "publish_date": "2025-04-03",
        "location": [
          "美國 密蘇里州",
          "阿肯色州",
          "田納西州",
          "密西西比州",
          "印第安納州",
          "伊利諾州",
          "肯塔基州",
          "奧克拉荷馬州",
          "密西根州",
          "內華達鎮"
        ],
        "summary": "美國中南部地區遭遇龍捲風與暴雨襲擊，造成至少1人死亡，超過35萬用戶斷電。預計未來幾天將有世代級洪災，部分地區可能降下38.1公分的雨量，河流可能決堤，引發災難性洪水。"
      }
    ]
  }
]